{
  "monitored_playlists": [],
  "downloads_folder": "~/Downloads",
  "external_drive_path": "/Volumes/My Passport/Music/iTunes/iTunes Media/Music/Unknown Artist/Unknown Album",
  "playlist_mapping": {
    "Disco+Melodic": "Disco & Melodic",
    "House": "House - Hot Since 82",
    "Worldtech": "Worldtech Latin Afro",
    "Tech House": "Tech House"
  },
  "poll_interval_minutes": 30,
  "file_watch_enabled": true,
  "auto_scan_playlists": [],
  "genre_folders": {
    "Disco+Melodic": "Disco & Melodic",
    "House": "House",
    "Worldtech": "Worldtech",
    "Tech House": "Tech House"
  }
}
